projen_study/__init__.py
projen_study/py.typed
projen_study/_jsii/__init__.py
projen_study/_jsii/projen-study@0.1.2.jsii.tgz
projen_study-0.1.2.dist-info/LICENSE
projen_study-0.1.2.dist-info/METADATA
projen_study-0.1.2.dist-info/WHEEL
projen_study-0.1.2.dist-info/top_level.txt
projen_study-0.1.2.dist-info/RECORD
